pydrime/__init__.py
pydrime/_version.py
pydrime/api.py
pydrime/auth.py
pydrime/cli_progress.py
pydrime/config.py
pydrime/download_helpers.py
pydrime/duplicate_finder.py
pydrime/duplicate_handler.py
pydrime/exceptions.py
pydrime/file_entries_manager.py
pydrime/logging.py
pydrime/models.py
pydrime/output.py
pydrime/progress.py
pydrime/upload_preview.py
pydrime/utils.py
pydrime/validation.py
pydrime/vault_crypto.py
pydrime/workspace_utils.py
pydrime/cli/__init__.py
pydrime/cli/adapters.py
pydrime/cli/download_command.py
pydrime/cli/file_management_commands.py
pydrime/cli/helpers.py
pydrime/cli/info_commands.py
pydrime/cli/init_command.py
pydrime/cli/list_commands.py
pydrime/cli/read_commands.py
pydrime/cli/server_commands.py
pydrime/cli/special_views_commands.py
pydrime/cli/sync_command.py
pydrime/cli/upload_command.py
pydrime/cli/utility_commands.py
pydrime/cli/vault_adapters.py
pydrime/cli/vault_commands.py
pydrime/cli/workspace_commands.py
pydrime-0.8.2.dist-info/licenses/LICENSE
pydrime-0.8.2.dist-info/METADATA
pydrime-0.8.2.dist-info/WHEEL
pydrime-0.8.2.dist-info/entry_points.txt
pydrime-0.8.2.dist-info/top_level.txt
pydrime-0.8.2.dist-info/RECORD
